{
    "id": 126739084,
    "name": "A101 The Challenge",
    "author": "ick567",
    "creators": ["Cduking"],
    "verifier": "ick567",
    "verification": "https://youtu.be/bw8YOuFCmGs",
    "percentToQualify": "100",
    "records": [
        {
            "user": "KellenGuu",
            "link": "https://youtu.be/gHHL6SnHTo",
            "percent": 100,
            "hz": 60
        },
        {
            "user": "IAmTheSolarFlare",
            "link": "https://youtu.be/GLOGKQl7iH4"
            "percent": 100,
            "hz": 60
        }
    ]
}
